exo/__init__.py
exo/api.py
exo/json.py
exo_pyface-0.1.0.dist-info/LICENSE
exo_pyface-0.1.0.dist-info/METADATA
exo_pyface-0.1.0.dist-info/WHEEL
exo_pyface-0.1.0.dist-info/top_level.txt
exo_pyface-0.1.0.dist-info/RECORD
