Metadata-Version: 2.1
Name: exo-pyface
Version: 0.1.0
Summary: UNKNOWN
Home-page: UNKNOWN
Author: Shankhanil Ghosh
Author-email: shankha.rik@gmail.com
License: UNKNOWN
Platform: UNKNOWN
